numerosprimosjm/operations.py
numerosprimosjm-1.0.dist-info/LICENSE.txt
numerosprimosjm-1.0.dist-info/METADATA
numerosprimosjm-1.0.dist-info/WHEEL
numerosprimosjm-1.0.dist-info/top_level.txt
numerosprimosjm-1.0.dist-info/RECORD
