Metadata-Version: 2.1
Name: numerosprimosjm
Version: 1.0
Summary: UNKNOWN
Home-page: UNKNOWN
Author: José María Amuedo
Author-email: jmmauedo@gmail.com
License: GNU GPLv3
Keywords: pyoperaciones mathematical operations
Platform: UNKNOWN
Classifier: Development Status :: 4 - Beta
Classifier: Intended Audience :: Developers
Classifier: Topic :: Utilities
Classifier: License :: OSI Approved :: GNU General Public License v3 (GPLv3)
Classifier: Programming Language :: Python :: 3
